LICENSE
README.md
pyproject.toml
gnucash_uk_vat/__init__.py
gnucash_uk_vat/__main__.py
gnucash_uk_vat/accounts.py
gnucash_uk_vat/accounts_gnucash.py
gnucash_uk_vat/accounts_piecash.py
gnucash_uk_vat/assist.py
gnucash_uk_vat/auth.py
gnucash_uk_vat/cli.py
gnucash_uk_vat/config.py
gnucash_uk_vat/device.py
gnucash_uk_vat/hmrc.py
gnucash_uk_vat/model.py
gnucash_uk_vat/operations.py
gnucash_uk_vat/test_service.py
gnucash_uk_vat/vat.py
gnucash_uk_vat/version.py
gnucash_uk_vat.egg-info/PKG-INFO
gnucash_uk_vat.egg-info/SOURCES.txt
gnucash_uk_vat.egg-info/dependency_links.txt
gnucash_uk_vat.egg-info/entry_points.txt
gnucash_uk_vat.egg-info/requires.txt
gnucash_uk_vat.egg-info/top_level.txt
test/test_fraud_api.py
tests/__init__.py
tests/test_models.py
tests/test_module.py
tests/test_vat.py
tests/unit/__init__.py
tests/unit/test_config.py