Metadata-Version: 2.4
Name: gnucash-uk-vat
Version: 1.8.5
Summary: UK HMRC VAT submission bridge for GnuCash users
Author-email: Cybermaggedon <mark@cyberapocalypse.co.uk>
License: GPL-3.0-or-later
Project-URL: Homepage, https://github.com/cybermaggedon/gnucash-uk-vat
Project-URL: Repository, https://github.com/cybermaggedon/gnucash-uk-vat
Project-URL: Issues, https://github.com/cybermaggedon/gnucash-uk-vat/issues
Project-URL: Documentation, https://github.com/cybermaggedon/gnucash-uk-vat/blob/main/README.md
Keywords: vat,hmrc,gnucash,accounting,uk,tax
Classifier: Programming Language :: Python :: 3
Classifier: Programming Language :: Python :: 3.9
Classifier: Programming Language :: Python :: 3.10
Classifier: Programming Language :: Python :: 3.11
Classifier: Programming Language :: Python :: 3.12
Classifier: Programming Language :: Python :: 3.13
Classifier: License :: OSI Approved :: GNU General Public License v3 or later (GPLv3+)
Classifier: Operating System :: OS Independent
Classifier: Development Status :: 4 - Beta
Classifier: Intended Audience :: End Users/Desktop
Classifier: Topic :: Office/Business :: Financial :: Accounting
Requires-Python: >=3.9
License-File: LICENSE
Requires-Dist: aiohttp
Requires-Dist: py-dmidecode
Requires-Dist: piecash
Requires-Dist: netifaces
Requires-Dist: tabulate
Provides-Extra: dev
Requires-Dist: pytest>=7.0.0; extra == "dev"
Requires-Dist: pytest-asyncio>=0.18.0; extra == "dev"
Requires-Dist: pytest-cov>=3.0.0; extra == "dev"
Requires-Dist: pytest-mock>=3.6.0; extra == "dev"
Requires-Dist: mypy>=1.0.0; extra == "dev"
Requires-Dist: types-tabulate; extra == "dev"
Requires-Dist: netifaces; extra == "dev"
Requires-Dist: aiohttp; extra == "dev"
Dynamic: license-file
